LudwigFIAP/__init__.py
LudwigFIAP/core.py
ludwigfiap_package-1.0.0.dist-info/METADATA
ludwigfiap_package-1.0.0.dist-info/WHEEL
ludwigfiap_package-1.0.0.dist-info/top_level.txt
ludwigfiap_package-1.0.0.dist-info/RECORD
